{
  "name": {
    "en": "Bee's Knees",
    "zh": "\u871c\u8702\u7684\u819d\u84cb"
  },
  "description": {
    "en": "A classic prohibition-era cocktail. The Bee's Knees combines gin, lemon juice, and honey syrup for a sweet and sour drink with a smooth finish. The name is thought to be slang for \"the best.\"",
    "zh": "\u4e00\u6b3e\u7d93\u5178\u7684\u7981\u9152\u6642\u4ee3\u96de\u5c3e\u9152\u3002\u871c\u8702\u7684\u819d\u84cb\u7d50\u5408\u4e86\u7434\u9152\u3001\u6ab8\u6aac\u6c41\u548c\u8702\u871c\u7cd6\u6f3f\uff0c\u88fd\u6210\u4e00\u7a2e\u9178\u751c\u53ef\u53e3\u3001\u53e3\u611f\u9806\u6ed1\u7684\u98f2\u54c1\u3002\u9019\u500b\u540d\u5b57\u88ab\u8a8d\u70ba\u662f\u201c\u6700\u597d\u7684\u201d\u7684\u4fda\u8a9e\u3002"
  },
  "historical_reference": {
    "en": "**Origin**: Prohibition Era, USA\n\nThe Bee's Knees cocktail emerged during the Prohibition era (1920-1933) in the United States. The less-than-high-quality gin available at the time was often masked by stronger flavors. Honey and lemon were used to make the gin more palatable:\n\n*   The name \"Bee's Knees\" was a popular slang term meaning \"the best\".\n*   First appeared in print in 1929 in *Here's How* by Judge Jr.",
    "zh": "**\u8d77\u6e90**\uff1a\u7f8e\u570b\u7981\u9152\u6642\u671f\n\n\u871c\u8702\u7684\u819d\u84cb\u96de\u5c3e\u9152\u51fa\u73fe\u5728\u7f8e\u570b\u7684\u7981\u9152\u6642\u671f\uff081920-1933 \u5e74\uff09\u3002 \u7576\u6642\u63d0\u4f9b\u7684\u54c1\u8cea\u4e0d\u4f73\u7684\u7434\u9152\u901a\u5e38\u88ab\u66f4\u6fc3\u90c1\u7684\u5473\u9053\u6240\u63a9\u84cb\u3002 \u8702\u871c\u548c\u6ab8\u6aac\u88ab\u7528\u4f86\u4f7f\u7434\u9152\u66f4\u7f8e\u5473\uff1a\n\n*   \u201c\u871c\u8702\u7684\u819d\u84cb\u201d\u9019\u500b\u540d\u5b57\u662f\u4e00\u500b\u6d41\u884c\u7684\u4fda\u8a9e\uff0c\u610f\u601d\u662f\u201c\u6700\u597d\u7684\u201d\u3002\n*   1929 \u5e74\u9996\u6b21\u51fa\u73fe\u5728 Judge Jr. \u7684 *Here's How* \u4e2d\u3002"
  },
  "technique": {
    "en": "Shake all ingredients with ice and strain into a chilled glass.",
    "zh": "\u5c07\u6240\u6709\u6750\u6599\u8207\u51b0\u584a\u6416\u52fb\uff0c\u7136\u5f8c\u6ffe\u5165\u51b0\u93ae\u7684\u676f\u5b50\u3002"
  },
  "garnish": {
    "en": "Lemon twist",
    "zh": "\u6ab8\u6aac\u76ae\u626d\u8f49"
  },
  "serve_in_glass": {
    "en": "Coupe or Cocktail Glass",
    "zh": "\u6dfa\u789f\u9999\u6ab3\u676f\u6216\u96de\u5c3e\u9152\u676f"
  },
  "appearance": {
    "en": "Pale yellow, slightly cloudy",
    "zh": "\u6de1\u9ec3\u8272\uff0c\u7565\u5e36\u6df7\u6fc1"
  },
  "allergens": [],
  "base_spirits": [
    {
      "amount": 60,
      "name": {
        "en": "Gin",
        "zh": "\u7434\u9152"
      },
      "unit": {
        "en": "ml",
        "zh": "\u6beb\u5347"
      },
      "rationale": {
        "en": "Provides the cocktail's main spirituous backbone and botanical complexity.",
        "zh": "\u63d0\u4f9b\u96de\u5c3e\u9152\u4e3b\u8981\u7684\u9152\u9ad4\u9aa8\u5e79\u548c\u690d\u7269\u6027\u8907\u96dc\u5ea6\u3002"
      }
    }
  ],
  "liqueurs": [],
  "ingredients": [
    {
      "amount": 22,
      "name": {
        "en": "Lemon Juice",
        "zh": "\u6ab8\u6aac\u6c41"
      },
      "unit": {
        "en": "ml",
        "zh": "\u6beb\u5347"
      },
      "rationale": {
        "en": "Adds acidity and balance to the sweetness of the honey.",
        "zh": "\u589e\u52a0\u9178\u5ea6\u4e26\u5e73\u8861\u8702\u871c\u7684\u751c\u5ea6\u3002"
      }
    },
    {
      "amount": 22,
      "name": {
        "en": "Honey Syrup (2:1)",
        "zh": "\u8702\u871c\u7cd6\u6f3f (2:1)"
      },
      "unit": {
        "en": "ml",
        "zh": "\u6beb\u5347"
      },
      "rationale": {
        "en": "Adds sweetness and a unique flavor profile.",
        "zh": "\u589e\u52a0\u751c\u5473\u548c\u7368\u7279\u7684\u98a8\u5473\u3002"
      }
    }
  ],
  "flavor_descriptors": [
    {
      "en": "Citrus",
      "zh": "\u67d1\u6a58"
    },
    {
      "en": "Floral",
      "zh": "\u82b1\u9999"
    },
    {
      "en": "Herbal",
      "zh": "\u8349\u672c"
    },
    {
      "en": "Fruity",
      "zh": "\u679c\u9999"
    }
  ],
  "flavor_profile": {
    "sweetness": 7,
    "sourness": 6,
    "booziness": 6,
    "body": 5,
    "complexity": 7,
    "bubbles": false
  }
}