{
  "name": {
    "en": "Red Russian",
    "zh": "\u7d05\u8272\u4fc4\u7f85\u65af"
  },
  "description": {
    "en": "**Simple and Potent**\n\nA straightforward cocktail combining vodka and coffee liqueur.\n\n*   Easy to make\n*   Strong coffee flavor\n*   Can be adjusted to taste",
    "zh": "**\u7c21\u55ae\u800c\u5f37\u70c8**\n\n\u5c07\u4f0f\u7279\u52a0\u548c\u5496\u5561\u5229\u53e3\u9152\u7d50\u5408\u7684\u7c21\u55ae\u96de\u5c3e\u9152\u3002\n\n*   \u6613\u65bc\u88fd\u4f5c\n*   \u6fc3\u90c1\u7684\u5496\u5561\u5473\n*   \u53ef\u4ee5\u6839\u64da\u53e3\u5473\u9032\u884c\u8abf\u6574"
  },
  "historical_reference": {
    "en": "**Origin**: Likely emerged during the Cold War era.\n\n*   Name implies a connection to Russia (vodka) and its then-antagonistic relationship with the West (the 'black' or 'red' color association).\n*   Its exact origin is murky, but the combination of vodka and coffee liqueur became popular in the mid-20th century.",
    "zh": "**\u8d77\u6e90**\uff1a\u53ef\u80fd\u51fa\u73fe\u5728\u51b7\u6230\u6642\u671f\u3002\n\n*   \u540d\u7a31\u6697\u793a\u4e86\u8207\u4fc4\u7f85\u65af\uff08\u4f0f\u7279\u52a0\uff09\u7684\u806f\u7e6b\uff0c\u4ee5\u53ca\u7576\u6642\u8207\u897f\u65b9\u7684\u6575\u5c0d\u95dc\u4fc2\uff08\u201c\u9ed1\u8272\u201d\u6216\u201c\u7d05\u8272\u201d\u7684\u984f\u8272\u806f\u60f3\uff09\u3002\n*   \u5176\u78ba\u5207\u8d77\u6e90\u5c1a\u4e0d\u6e05\u695a\uff0c\u4f46\u4f0f\u7279\u52a0\u548c\u5496\u5561\u5229\u53e3\u9152\u7684\u7d44\u5408\u572820\u4e16\u7d00\u4e2d\u8449\u958b\u59cb\u6d41\u884c\u3002"
  },
  "technique": {
    "en": "Build; Pour vodka and coffee liqueur into an Old Fashioned glass filled with ice. Stir gently.",
    "zh": "\u514c\u548c\u6cd5; \u5c07\u4f0f\u7279\u52a0\u548c\u5496\u5561\u5229\u53e3\u9152\u5012\u5165\u88dd\u6eff\u51b0\u584a\u7684\u53e4\u5178\u676f\u4e2d\u3002 \u8f15\u8f15\u652a\u62cc\u3002"
  },
  "garnish": {
    "en": "None typically",
    "zh": "\u901a\u5e38\u6c92\u6709"
  },
  "serve_in_glass": {
    "en": "Old Fashioned glass",
    "zh": "\u53e4\u5178\u676f"
  },
  "appearance": {
    "en": "Dark brown, opaque",
    "zh": "\u6df1\u68d5\u8272\uff0c\u4e0d\u900f\u660e"
  },
  "allergens": [],
  "base_spirits": [
    {
      "amount": 50,
      "name": {
        "en": "Generic Vodka",
        "zh": "\u4f0f\u7279\u52a0"
      },
      "unit": {
        "en": "ml",
        "zh": "\u6beb\u5347"
      },
      "rationale": {
        "en": "Provides the alcoholic base and a neutral flavor profile.",
        "zh": "\u63d0\u4f9b\u9152\u7cbe\u57fa\u5e95\u548c\u4e2d\u6027\u7684\u98a8\u5473\u3002"
      }
    }
  ],
  "liqueurs": [
    {
      "amount": 25,
      "name": {
        "en": "Generic Coffee Liqueur",
        "zh": "\u5496\u5561\u5229\u53e3\u9152"
      },
      "unit": {
        "en": "ml",
        "zh": "\u6beb\u5347"
      },
      "rationale": {
        "en": "Adds sweetness and coffee flavor.",
        "zh": "\u589e\u52a0\u751c\u5473\u548c\u5496\u5561\u5473\u3002"
      }
    }
  ],
  "ingredients": [],
  "flavor_descriptors": [
    {
      "en": "Coffee",
      "zh": "\u5496\u5561"
    },
    {
      "en": "Bitter",
      "zh": "\u82e6\u5473"
    },
    {
      "en": "Chocolate",
      "zh": "\u5de7\u514b\u529b"
    }
  ],
  "flavor_profile": {
    "sweetness": 4,
    "sourness": 1,
    "booziness": 7,
    "body": 5,
    "complexity": 4,
    "bubbles": false
  }
}