{
  "name": {
    "en": "Dirty Mother",
    "zh": "黯淡的母親"
  },
  "description": {
    "en": "Dirty Mother is a simple yet flavorful coffee liqueur cocktail. It combines brandy as a base with coffee liqueur, creating a rich, after-dinner coffee-like experience. The unique notes of brandy blend seamlessly with the coffee liqueur, offering a touch of sweetness and nutty aroma, with a smooth texture that leaves a warm aftertaste.\n\n*   Rich and creamy\n*   Easy to make\n*   Good for dessert",
    "zh": "「黯淡的母親」（Dirty Mother）是一款簡單卻深具風味的咖啡香甜酒調酒。\n\n以白蘭地為基底，與咖啡香甜酒混合，創造出如餐後咖啡般的醇厚口感。\n\n白蘭地的獨特風味與咖啡香甜酒完美融合，帶來一絲甜美與堅果香氣，口感滑順，在舌尖留下溫暖的餘韻。儘管名稱略帶戲謔，這款調酒卻能撫慰疲憊的心靈，如同在深夜中，為辛勞的母親帶來一絲慰藉。"
  },
  "historical_reference": {
    "en": "",
    "zh": ""
  },
  "technique": {
    "en": "Build over ice",
    "zh": "在冰上調製"
  },
  "garnish": {
    "en": "Grated nutmeg or chocolate shavings (optional)",
    "zh": "磨碎的肉荳蔻或巧克力屑（可選）"
  },
  "serve_in_glass": {
    "en": "Old-fashioned glass",
    "zh": "古典杯"
  },
  "appearance": {
    "en": "Light brown",
    "zh": "淺棕色"
  },
  "allergens": [],
  "base_spirits": [
    {
      "amount": 60,
      "name": {
        "en": "Brandy",
        "zh": "白蘭地"
      },
      "unit": {
        "en": "ml",
        "zh": "毫升"
      },
      "rationale": {
        "en": "Provides the alcoholic base and warm fruit notes.",
        "zh": "提供酒精基底和溫暖的水果味。"
      }
    }
  ],
  "liqueurs": [
    {
      "amount": 30,
      "name": {
        "en": "Coffee Liqueur",
        "zh": "咖啡利口酒"
      },
      "unit": {
        "en": "ml",
        "zh": "毫升"
      },
      "rationale": {
        "en": "Adds coffee flavor and sweetness.",
        "zh": "增加咖啡味和甜味。"
      }
    }
  ],
  "ingredients": [],
  "flavor_descriptors": [
    {
      "en": "Chocolate",
      "zh": "朱古力"
    },
    {
      "en": "Coffee",
      "zh": "咖啡"
    },
    {
      "en": "Vanilla",
      "zh": "香草"
    },
    {
      "en": "Nutty",
      "zh": "堅果"
    }
  ],
  "flavor_profile": {
    "sweetness": 7,
    "sourness": 1,
    "booziness": 6,
    "body": 4,
    "complexity": 5,
    "bubbles": false
  }
}